RTL/rom_memory.v
module rom_memory #(
    parameter DATA_WIDTH = 32,
    parameter ADDR_WIDTH = 5)
(   input wire [ADDR_WIDTH-1:0] addr,
    input wire read_en,

    output reg [DATA_WIDTH-1:0] data,
    output reg valid
);
reg [31:0] local_data_reg [0:31];

initial begin
        local_data_reg[0]  = 32'hA0; local_data_reg[1]  = 32'hA1; local_data_reg[2]  = 32'hA2; local_data_reg[3]  = 32'hA3;
        local_data_reg[4]  = 32'hA4; local_data_reg[5]  = 32'hA5; local_data_reg[6]  = 32'hA6; local_data_reg[7]  = 32'hA7;
        local_data_reg[8]  = 32'hA8; local_data_reg[9]  = 32'hA9; local_data_reg[10] = 32'hAA; local_data_reg[11] = 32'hAB;
        local_data_reg[12] = 32'hAC; local_data_reg[13] = 32'hAD; local_data_reg[14] = 32'hAE; local_data_reg[15] = 32'hAF;
        local_data_reg[16] = 32'hB0; local_data_reg[17] = 32'hB1; local_data_reg[18] = 32'hB2; local_data_reg[19] = 32'hB3;
        local_data_reg[20] = 32'hB4; local_data_reg[21] = 32'hB5; local_data_reg[22] = 32'hB6; local_data_reg[23] = 32'hB7;
        local_data_reg[24] = 32'hB8; local_data_reg[25] = 32'hB9; local_data_reg[26] = 32'hBA; local_data_reg[27] = 32'hBB;
        local_data_reg[28] = 32'hBC; local_data_reg[29] = 32'hBD; local_data_reg[30] = 32'hBE; local_data_reg[31] = 32'hBF;
    end

always@(*)begin
    if(read_en)begin 
        data <= local_data_reg[addr];
        valid <= 1;
    end else begin 
        data <= 0;
        valid <= 0;
    end
end
endmodule

RTL/axi_slave_fsm.v
module axi_slave_fsm #(
    parameter DATA_WIDTH = 69
)(
    // Global input signals     
    input  wire                    s_axi_aclk,
    input  wire                    s_axi_aresetn,

    // Write address input channels 
    input  wire [31:0]             s_axi_awaddr,
    input  wire                    s_axi_awvalid,

    // Write data input channels 
    input  wire [31:0]             s_axi_wdata,
    input  wire [3:0]              s_axi_wstrb,
    input  wire                    s_axi_wvalid,

    // Write response input channels
    input  wire                    s_axi_bready,

    // Read address input channels
    input  wire [31:0]             s_axi_araddr,
    input  wire                    s_axi_arvalid,
    input  wire [31:0]             s_axi_rdata_rom,
    // Read data input channels 
    input  wire                    s_axi_rready,    //from main not rom

    input wire                     mem_valid,//comes from rom

    // Async fifo status signals
    input  wire                    wfifo_full,

    // Write address output channels 
    output reg                     s_axi_awready,
    // Write data output channels 
    output reg                     s_axi_wready,
    // Write response output channels
    output reg  [1:0]              s_axi_bresp,
    output reg                     s_axi_bvalid,

    // Read address output channels 
    output reg                     s_axi_arready,
    // Read data output channels
    output reg [31:0]              s_axi_rdata,
    output reg  [1:0]              s_axi_rresp,
    output reg                     s_axi_rvalid,
    output reg[4:0]                s_axi_rid,
    output reg                     s_axi_ext_rena,

    // Async fifo write interface
    output reg                     wfifo_wen,
    output reg  [DATA_WIDTH-1:0]   wfifo_wdata
);

parameter SW_IDLE = 2'b00;
parameter SW_WAITING = 2'b01;
parameter SW_WRITING = 2'b11;
parameter SW_RESPONSE = 2'b10;

parameter SR_IDLE = 2'b00;
parameter SR_READING = 2'b01;
parameter SR_RESPONSE  = 2'b11;

reg [1:0] sw_curr_state, sw_next_state;
reg [1:0] sr_curr_state, sr_next_state;
reg [31:0] axi_awaddr_reg, axi_wdata_reg;
reg [31:0] axi_araddr_reg;
reg [3:0] axi_wstrb_reg;
reg sw_axi_awvalid_recieved, sw_axi_wvalid_recieved;
reg sr_axi_arvalid_recieved,sr_axi_rvalid_recieved;
reg mem_valid_recieved;
// reg aw_hs_done, w_hs_done;

// wire sw_awaddr_handshake = (s_axi_awvalid && s_axi_awready) || aw_hs_done;
// wire sw_wdata_handshake = (s_axi_wvalid && s_axi_wready) || w_hs_done;

always@(*)begin
    if(!s_axi_aresetn)begin
        sw_next_state <= SW_IDLE;
    end else begin
        case(sw_curr_state)
            SW_IDLE:begin
                if(sw_axi_awvalid_recieved || sw_axi_wvalid_recieved)begin
                    sw_next_state <= SW_WAITING;
                end else begin
                    sw_next_state <= SW_IDLE;
                end
            end

            SW_WAITING:begin
                if(sw_axi_awvalid_recieved && sw_axi_wvalid_recieved && !wfifo_full)begin
                    sw_next_state <= SW_WRITING;
                end else begin
                    sw_next_state <= SW_WAITING;
                end
            end

            SW_WRITING:begin
                // if(sw_awaddr_handshake && sw_wdata_handshake)begin
                //     sw_next_state <= SW_RESPONSE;
                // end else begin
                sw_next_state <= SW_RESPONSE;
                // end
            end

            SW_RESPONSE:begin
                if(s_axi_bready)begin
                    sw_next_state <= SW_IDLE;
                end else begin
                    sw_next_state <= SW_RESPONSE;
                end
            end 

            default:begin
                sw_next_state <= SW_IDLE;
            end
        endcase
    end
end

always@(*)begin
    if(!s_axi_aresetn)begin
        sr_next_state <= SR_IDLE;
    end else begin
        case(sr_curr_state)
            SR_IDLE:begin
                if(sr_axi_arvalid_recieved)begin
                    sr_next_state <= SR_READING;
                end else begin
                    sr_next_state <= SR_IDLE;
                end
            end

            SR_READING:begin
                if(mem_valid_recieved )begin
                    sr_next_state <= SR_RESPONSE;
                end else begin
                sr_next_state <= SR_READING;
                end
            end

            SR_RESPONSE:begin
                if(s_axi_rready)begin
                    sr_next_state <= SR_IDLE;
                end else begin
                    sr_next_state <= SR_RESPONSE;
                end
            end 

            default:begin
                sr_next_state <= SR_IDLE;
            end
        endcase
    end
end

always@(posedge s_axi_aclk or negedge s_axi_aresetn)begin
    if(!s_axi_aresetn)begin
        s_axi_awready <= 0;
        s_axi_wready <= 0;
        s_axi_bresp <= 0;
        s_axi_bvalid <= 0;
        sw_curr_state <= SW_IDLE;
        wfifo_wen <= 0;
        wfifo_wdata <= 0;
        axi_awaddr_reg <= 0;
        axi_wdata_reg <= 0;
        axi_wstrb_reg <= 0;
        sw_axi_awvalid_recieved <= 0;
        sw_axi_wvalid_recieved <= 0;
    end else begin
        sw_curr_state <= sw_next_state;
        if (sw_curr_state == SW_IDLE || sw_curr_state == SW_WAITING)begin
           if(s_axi_awvalid && !sw_axi_awvalid_recieved)begin
                sw_axi_awvalid_recieved <= 1;
                axi_awaddr_reg <= s_axi_awaddr;
            end 

            if(s_axi_wvalid && !sw_axi_wvalid_recieved)begin
                sw_axi_wvalid_recieved <= 1;
                axi_wdata_reg <= s_axi_wdata;
                axi_wstrb_reg <= s_axi_wstrb;
            end
        end

        case(sw_curr_state)

            SW_IDLE:begin
                s_axi_awready <= 0;
                s_axi_wready <= 0;
                s_axi_bresp <= 0;
                s_axi_bvalid <=0;
                wfifo_wen <= 0;
                wfifo_wdata <= 0;
            end

            SW_WAITING:begin
                s_axi_awready <= 0;
                s_axi_wready <= 0;
                s_axi_bresp <= 0;
                s_axi_bvalid <=0;
                wfifo_wen <= 0;
                wfifo_wdata <= 0;
            end

            SW_WRITING:begin
                // s_axi_awready <= !sw_awaddr_handshake;
                // s_axi_wready <= !sw_wdata_handshake;
                s_axi_awready <= 1'b1;
                s_axi_wready <= 1'b1;
                s_axi_bresp <= 0;
                s_axi_bvalid <=0;

                // if (s_axi_awvalid && s_axi_awready) aw_hs_done <= 1;
                // if (s_axi_wvalid && s_axi_wready) w_hs_done <= 1;
                
                // if (sw_awaddr_handshake && sw_wdata_handshake) begin
                //     wfifo_wen <= 1;
                //     wfifo_wdata <= {1'b1, axi_awaddr_reg, axi_wdata_reg, axi_wstrb_reg};
                // end else begin
                //     wfifo_wen <= 0;
                // end  
                 wfifo_wen <= 1;
                wfifo_wdata <= {1'b1, axi_awaddr_reg, axi_wdata_reg, axi_wstrb_reg};
            end

            SW_RESPONSE:begin
                s_axi_awready <= 0;
                s_axi_wready <= 0;
                s_axi_bresp <= 0;
                s_axi_bvalid <= 1;
                wfifo_wen <= 0;
                wfifo_wdata <= 0;
                sw_axi_awvalid_recieved <= 0;
                sw_axi_wvalid_recieved <= 0;
            end
        endcase
    end
end 

always@(posedge s_axi_aclk or negedge s_axi_aresetn)begin
    if(!s_axi_aresetn)begin
        s_axi_arready <= 0;
        s_axi_rresp <= 0;
        s_axi_rvalid <= 0;
        sr_curr_state <= SR_IDLE;
        axi_araddr_reg <= 0;
        sr_axi_arvalid_recieved <= 0;
        s_axi_rid<=0;
        s_axi_ext_rena<=0;
    end else begin
        sr_curr_state <= sr_next_state;
        if (sr_curr_state == SR_IDLE || sr_curr_state == SR_READING)begin
            if(s_axi_arvalid && !sr_axi_arvalid_recieved)begin
                sr_axi_arvalid_recieved <= 1;
                axi_araddr_reg <= s_axi_araddr;
            end 
        end

        case(sr_curr_state)
            SR_IDLE:begin
                s_axi_arready <= 0;
                s_axi_rresp <= 0;
                s_axi_rvalid <=0;
                s_axi_rid <= 0;
                s_axi_ext_rena <= 0;
            end

            SR_READING:begin
                s_axi_arready <= 1'b1;
                
                //to rom 
                s_axi_rid <= axi_araddr_reg[4:0];
                s_axi_ext_rena <= 1;

                //from rom 
                if(mem_valid)begin
                    s_axi_rdata <= s_axi_rdata_rom;
                    mem_valid_recieved <= 1'b1;
                end
                s_axi_rresp <= 0;
                s_axi_rvalid <=0;
            end

            SR_RESPONSE:begin
                s_axi_arready <= 0;
                s_axi_rresp <= 0;
                s_axi_rvalid <= 1;
                sr_axi_arvalid_recieved <= 0;
                sr_axi_rvalid_recieved <= 0;
                mem_valid_recieved <= 0;
                s_axi_rid<= 0;
                s_axi_ext_rena <= 0;
            end
        endcase
    end
end
endmodule

TB/axi_slave_final.v
module tb_final_axi;

    parameter DATA_WIDTH = 69;

    reg s_axi_aclk;
    reg s_axi_aresetn;

    reg [31:0] s_axi_awaddr;
    reg s_axi_awvalid;
    reg [31:0] s_axi_wdata;
    reg [3:0] s_axi_wstrb;
    reg s_axi_wvalid;
    reg s_axi_bready;

    reg [31:0] s_axi_araddr;
    reg s_axi_arvalid;
    reg s_axi_rready;

    reg wfifo_full;

    wire s_axi_awready;
    wire s_axi_wready;
    wire [1:0] s_axi_bresp;
    wire s_axi_bvalid;

    wire s_axi_arready;
    wire [31:0] s_axi_rdata;
    wire [1:0] s_axi_rresp;
    wire s_axi_rvalid;

    wire [4:0] s_axi_rid;
    wire s_axi_ext_rena;
    wire wfifo_wen;
    wire [DATA_WIDTH-1:0] wfifo_wdata;

    wire [31:0] rom_data_wire;
    wire rom_valid_wire;

    axi_slave_fsm #(
        .DATA_WIDTH(DATA_WIDTH)
    ) fsm_inst (
        .s_axi_aclk(s_axi_aclk),
        .s_axi_aresetn(s_axi_aresetn),
        .s_axi_awaddr(s_axi_awaddr),
        .s_axi_awvalid(s_axi_awvalid),
        .s_axi_wdata(s_axi_wdata),
        .s_axi_wstrb(s_axi_wstrb),
        .s_axi_wvalid(s_axi_wvalid),
        .s_axi_bready(s_axi_bready),
        .s_axi_araddr(s_axi_araddr),
        .s_axi_arvalid(s_axi_arvalid),
        .s_axi_rdata_rom(rom_data_wire),
        .s_axi_rready(s_axi_rready),
        .mem_valid(rom_valid_wire),
        .wfifo_full(wfifo_full),
        .s_axi_awready(s_axi_awready),
        .s_axi_wready(s_axi_wready),
        .s_axi_bresp(s_axi_bresp),
        .s_axi_bvalid(s_axi_bvalid),
        .s_axi_arready(s_axi_arready),
        .s_axi_rdata(s_axi_rdata),
        .s_axi_rresp(s_axi_rresp),
        .s_axi_rvalid(s_axi_rvalid),
        .s_axi_rid(s_axi_rid),
        .s_axi_ext_rena(s_axi_ext_rena),
        .wfifo_wen(wfifo_wen),
        .wfifo_wdata(wfifo_wdata)
    );

    rom_memory #(
        .DATA_WIDTH(32),
        .ADDR_WIDTH(5)
    ) rom_inst (
        .addr(s_axi_rid),
        .read_en(s_axi_ext_rena),
        .data(rom_data_wire),
        .valid(rom_valid_wire)
    );

    initial begin
        s_axi_aclk = 0;
        forever #5 s_axi_aclk = ~s_axi_aclk;
    end

    task axi_write;
        input [31:0] addr;
        input [31:0] data;
        begin
            @(posedge s_axi_aclk);
            s_axi_awaddr = addr;
            s_axi_wdata = data;
            s_axi_wstrb = 4'b1111;
            s_axi_awvalid = 1;
            s_axi_wvalid = 1;
            s_axi_bready = 1;

            wait(s_axi_awready && s_axi_wready);
            @(posedge s_axi_aclk);
            s_axi_awvalid = 0;
            s_axi_wvalid = 0;

            wait(s_axi_bvalid);
            @(posedge s_axi_aclk);
            s_axi_bready = 0;
        end
    endtask

    task axi_read;
        input [31:0] addr;
        begin
            @(posedge s_axi_aclk);
            s_axi_araddr = addr;
            s_axi_arvalid = 1;
            s_axi_rready = 1;

            wait(s_axi_arready);
            @(posedge s_axi_aclk);
            s_axi_arvalid = 0;

            wait(s_axi_rvalid);
            $display("Time: %0t | READ ADDR: %0h | RDATA: %0h", $time, addr, s_axi_rdata);
            @(posedge s_axi_aclk);
            s_axi_rready = 0;
        end
    endtask

    initial begin
        $dumpfile("axi_tb.vcd");
        $dumpvars(0, tb_final_axi);

        s_axi_aresetn = 0;
        s_axi_awaddr = 0;
        s_axi_awvalid = 0;
        s_axi_wdata = 0;
        s_axi_wstrb = 0;
        s_axi_wvalid = 0;
        s_axi_bready = 0;
        s_axi_araddr = 0;
        s_axi_arvalid = 0;
        s_axi_rready = 0;
        wfifo_full = 0;

        #20;
        s_axi_aresetn = 1;
        #20;

        axi_read(32'h00000000);
        #10;
        
        axi_read(32'h00000003);
        #10;

        axi_write(32'h00000010, 32'hDEADBEEF);
        #10;

        axi_read(32'h00000007);
        #10;

        $finish;
    end

endmodule

axi_tb.vcd
$date
	Fri Jun 05 17:31:30 2026
$end
$version
	Icarus Verilog
$end
$timescale
	1s
$end
$scope module tb_final_axi $end
$var wire 1 ! wfifo_wen $end
$var wire 69 " wfifo_wdata [68:0] $end
$var wire 1 # s_axi_wready $end
$var wire 1 $ s_axi_rvalid $end
$var wire 2 % s_axi_rresp [1:0] $end
$var wire 5 & s_axi_rid [4:0] $end
$var wire 32 ' s_axi_rdata [31:0] $end
$var wire 1 ( s_axi_ext_rena $end
$var wire 1 ) s_axi_bvalid $end
$var wire 2 * s_axi_bresp [1:0] $end
$var wire 1 + s_axi_awready $end
$var wire 1 , s_axi_arready $end
$var wire 1 - rom_valid_wire $end
$var wire 32 . rom_data_wire [31:0] $end
$var parameter 32 / DATA_WIDTH $end
$var reg 1 0 s_axi_aclk $end
$var reg 32 1 s_axi_araddr [31:0] $end
$var reg 1 2 s_axi_aresetn $end
$var reg 1 3 s_axi_arvalid $end
$var reg 32 4 s_axi_awaddr [31:0] $end
$var reg 1 5 s_axi_awvalid $end
$var reg 1 6 s_axi_bready $end
$var reg 1 7 s_axi_rready $end
$var reg 32 8 s_axi_wdata [31:0] $end
$var reg 4 9 s_axi_wstrb [3:0] $end
$var reg 1 : s_axi_wvalid $end
$var reg 1 ; wfifo_full $end
$scope module fsm_inst $end
$var wire 1 0 s_axi_aclk $end
$var wire 32 < s_axi_araddr [31:0] $end
$var wire 1 2 s_axi_aresetn $end
$var wire 1 3 s_axi_arvalid $end
$var wire 32 = s_axi_awaddr [31:0] $end
$var wire 1 5 s_axi_awvalid $end
$var wire 1 6 s_axi_bready $end
$var wire 1 7 s_axi_rready $end
$var wire 32 > s_axi_wdata [31:0] $end
$var wire 4 ? s_axi_wstrb [3:0] $end
$var wire 1 : s_axi_wvalid $end
$var wire 1 ; wfifo_full $end
$var wire 32 @ s_axi_rdata_rom [31:0] $end
$var wire 1 - mem_valid $end
$var parameter 32 A DATA_WIDTH $end
$var parameter 2 B SR_IDLE $end
$var parameter 2 C SR_READING $end
$var parameter 2 D SR_RESPONSE $end
$var parameter 2 E SW_IDLE $end
$var parameter 2 F SW_RESPONSE $end
$var parameter 2 G SW_WAITING $end
$var parameter 2 H SW_WRITING $end
$var reg 32 I axi_araddr_reg [31:0] $end
$var reg 32 J axi_awaddr_reg [31:0] $end
$var reg 32 K axi_wdata_reg [31:0] $end
$var reg 4 L axi_wstrb_reg [3:0] $end
$var reg 1 M mem_valid_recieved $end
$var reg 1 , s_axi_arready $end
$var reg 1 + s_axi_awready $end
$var reg 2 N s_axi_bresp [1:0] $end
$var reg 1 ) s_axi_bvalid $end
$var reg 1 ( s_axi_ext_rena $end
$var reg 32 O s_axi_rdata [31:0] $end
$var reg 5 P s_axi_rid [4:0] $end
$var reg 2 Q s_axi_rresp [1:0] $end
$var reg 1 $ s_axi_rvalid $end
$var reg 1 # s_axi_wready $end
$var reg 1 R sr_axi_arvalid_recieved $end
$var reg 1 S sr_axi_rvalid_recieved $end
$var reg 2 T sr_curr_state [1:0] $end
$var reg 2 U sr_next_state [1:0] $end
$var reg 1 V sw_axi_awvalid_recieved $end
$var reg 1 W sw_axi_wvalid_recieved $end
$var reg 2 X sw_curr_state [1:0] $end
$var reg 2 Y sw_next_state [1:0] $end
$var reg 69 Z wfifo_wdata [68:0] $end
$var reg 1 ! wfifo_wen $end
$upscope $end
$scope module rom_inst $end
$var wire 5 [ addr [4:0] $end
$var wire 1 ( read_en $end
$var parameter 32 \ ADDR_WIDTH $end
$var parameter 32 ] DATA_WIDTH $end
$var reg 32 ^ data [31:0] $end
$var reg 1 - valid $end
$upscope $end
$scope task axi_read $end
$var reg 32 _ addr [31:0] $end
$upscope $end
$scope task axi_write $end
$var reg 32 ` addr [31:0] $end
$var reg 32 a data [31:0] $end
$upscope $end
$upscope $end
$enddefinitions $end
$comment Show the parameter values. $end
$dumpall
b100000 ]
b101 \
b11 H
b1 G
b10 F
b0 E
b11 D
b1 C
b0 B
b1000101 A
b1000101 /
$end
#0
$dumpvars
bx a
bx `
bx _
b0 ^
b0 [
b0 Z
b0 Y
b0 X
0W
0V
b0 U
b0 T
xS
0R
b0 Q
b0 P
bx O
b0 N
xM
b0 L
b0 K
b0 J
b0 I
b0 @
b0 ?
b0 >
b0 =
b0 <
0;
0:
b0 9
b0 8
07
06
05
b0 4
03
02
b0 1
00
b0 .
0-
0,
0+
b0 *
0)
0(
bx '
b0 &
b0 %
0$
0#
b0 "
0!
$end
#5
10
#10
00
#15
10
#20
00
12
#25
10
#30
00
#35
10
#40
00
b0 _
#45
b1 U
1R
17
13
10
#50
00
#55
b1 T
10
#60
00
#65
1-
b10100000 .
b10100000 @
b10100000 ^
1(
1,
10
#70
00
#75
b11 U
1M
b10100000 '
b10100000 O
03
10
#80
00
#85
b0 U
b11 T
10
#90
00
#95
0-
b0 .
b0 @
b0 ^
0(
0M
0S
0R
1$
0,
b0 T
10
#100
00
#105
0$
07
10
#110
00
#115
b1 U
b11 I
1R
17
13
b11 1
b11 <
10
b11 _
#120
00
#125
b1 T
10
#130
00
#135
1-
b10100011 .
b10100011 @
b10100011 ^
1(
b11 &
b11 P
b11 [
1,
10
#140
00
#145
b11 U
1M
b10100011 '
b10100011 O
03
10
#150
00
#155
b0 U
b11 T
10
#160
00
#165
0-
b0 .
b0 @
b0 ^
0(
b0 &
b0 P
b0 [
0M
0R
1$
0,
b0 T
10
#170
00
#175
0$
07
10
#180
00
#185
b1 Y
b1111 L
b11011110101011011011111011101111 K
1W
b10000 J
1V
16
1:
15
b1111 9
b1111 ?
b11011110101011011011111011101111 8
b11011110101011011011111011101111 >
b10000 4
b10000 =
10
b11011110101011011011111011101111 a
b10000 `
#190
00
#195
b11 Y
b1 X
10
#200
00
#205
b10 Y
b11 X
10
#210
00
#215
b0 Y
b100000000000000000000000000010000110111101010110110111110111011111111 "
b100000000000000000000000000010000110111101010110110111110111011111111 Z
1!
1#
1+
b10 X
10
#220
00
#225
0W
0V
b0 "
b0 Z
0!
1)
0#
0+
b0 X
0:
05
10
#230
00
#235
0)
06
10
#240
00
#245
b1 U
b111 I
1R
17
13
b111 1
b111 <
10
b111 _
#250
00
#255
b1 T
10
#260
00
#265
1-
b10100111 .
b10100111 @
b10100111 ^
1(
b111 &
b111 P
b111 [
1,
10
#270
00
#275
b11 U
1M
b10100111 '
b10100111 O
03
10
#280
00
#285
b0 U
b11 T
10
#290
00
#295
0-
b0 .
b0 @
b0 ^
0(
b0 &
b0 P
b0 [
0M
0R
1$
0,
b0 T
10
#300
00
#305
0$
07
10
