RTL/async_fifo_core.v
module async_fifo_core #(
    // 32 bit address , 32 bit write data , 4 bit strobe width , 1 bit read/write
    parameter DATA_WIDTH = 69,
    // for r_ptr and w_ptr size
    parameter ADDR_WIDTH = 4
)(
    // Write Domain Inputs (AXI Clock Domain)
    input  wire                    wclk,
    input  wire                    wrst_n,
    input  wire                    winc,
    input  wire [DATA_WIDTH-1:0]   wdata,
    // Read Domain Inputs (APB Clock Domain)
    input  wire                    rclk,
    input  wire                    rrst_n,
    input  wire                    rinc,

    // Write Domain Inputs (AXI Clock Domain)
    output reg                     wfull,
    // Read Domain Inputs (APB Clock Domain)
    output wire [DATA_WIDTH-1:0]   rdata,
    output reg                     rempty

);

wire [ADDR_WIDTH:0] wptr_gray, rptr_gray;
// ensures rempty comes on the correct clk or it comes one clk late 
wire [ADDR_WIDTH:0] rptr_next = rptr + (rinc && !rempty);
wire [ADDR_WIDTH:0] rptr_gray_next = rptr_next ^ (rptr_next >> 1);
// ensures wfull comes on the correct clk or it comes one clk late
wire [ADDR_WIDTH:0] wptr_next = wptr + (winc && !wfull);
wire [ADDR_WIDTH:0] wptr_gray_next = wptr_next ^ (wptr_next >> 1);


// MSB of ptr is used to determine wrap around condition
// FIFO stores address alongside the actual data 
reg [ADDR_WIDTH:0] wptr, rptr;
reg [ADDR_WIDTH:0] rptr_gray_sync1, rptr_gray_sync2,wptr_gray_sync1, wptr_gray_sync2;
reg [DATA_WIDTH-1:0] async_fifo [2**ADDR_WIDTH-1:0];

assign wptr_gray = wptr^(wptr>> 1);
assign rptr_gray = rptr^(rptr>> 1);
assign rdata = async_fifo[rptr[ADDR_WIDTH-1:0]];

// Negedge rst prevent random power spikes in rst track to trigger rst
always@(posedge wclk or negedge wrst_n)begin
    if (wrst_n == 0) begin
        wfull <= 0;
        wptr <= 0;
    end else begin
    if(wfull!=1 && winc ==1)begin
        async_fifo[wptr[ADDR_WIDTH-1:0]] <= wdata;
        wptr <= wptr + 1;
    end
    // ensures that write pointer can write till only locations above read pointer even after wrap around
    wfull <= (wptr_gray_next == {~rptr_gray_sync2[ADDR_WIDTH:ADDR_WIDTH-1], rptr_gray_sync2[ADDR_WIDTH-2:0]});
    end
end

always@(posedge rclk or negedge rrst_n)begin
    if (rrst_n == 0) begin
        rempty <= 1;
        rptr <= 0;
    end else if (rempty!=1 && rinc ==1)begin
        rptr <= rptr + 1;
    end
    rempty <= (rptr_gray_next == wptr_gray_sync2);
end

// Synchronization of read pointer to domain of write pointer clk
always@(posedge wclk or negedge wrst_n)begin
    if (wrst_n==0) begin
    rptr_gray_sync1 <=0;
    rptr_gray_sync2 <=0;
    end else begin 
    rptr_gray_sync1 <= rptr_gray;
    rptr_gray_sync2 <= rptr_gray_sync1;
    end
end

// Synchronization of write pointer to domain of read pointer clk
always@(posedge rclk or negedge rrst_n)begin
    if (rrst_n==0) begin
    wptr_gray_sync1 <=0;
    wptr_gray_sync2 <=0;
    end else begin 
    wptr_gray_sync1 <= wptr_gray;
    wptr_gray_sync2 <= wptr_gray_sync1;
    end
end

endmodule

TB/async_fifo_tb.v
`timescale 1ns/1ps

module async_fifo_tb;

    parameter DATA_WIDTH = 69;
    parameter ADDR_WIDTH = 4;

    reg                    wclk;
    reg                    wrst_n;
    reg                    winc;
    reg [DATA_WIDTH-1:0]   wdata;

    reg                    rclk;
    reg                    rrst_n;
    reg                    rinc;

    wire                   wfull;
    wire [DATA_WIDTH-1:0]  rdata;
    wire                   rempty;

    async_fifo_core #(
        .DATA_WIDTH(DATA_WIDTH),
        .ADDR_WIDTH(ADDR_WIDTH)
    ) uut (
        .wclk(wclk),
        .wrst_n(wrst_n),
        .winc(winc),
        .wdata(wdata),
        .rclk(rclk),
        .rrst_n(rrst_n),
        .rinc(rinc),
        .wfull(wfull),
        .rdata(rdata),
        .rempty(rempty)
    );

    always #5  wclk = ~wclk;  // 100MHz Write Clock
    always #12 rclk = ~rclk;  // ~41.6MHz Read Clock (Asynchronous, slower)

    integer i;

    initial begin
        wclk   = 0;
        wrst_n = 0;
        winc   = 0;
        wdata  = 0;

        rclk   = 0;
        rrst_n = 0;
        rinc   = 0;

        #30;
        wrst_n = 1;
        rrst_n = 1;
        #20;

        @(posedge wclk);
        for (i = 1; i <= 20; i = i + 1) begin
            if (!wfull) begin
                winc  = 1;
                wdata = i;
            end else begin
                winc  = 1; 
                wdata = 999; 
            end
            @(posedge wclk);
        end
        winc = 0;

        #200;

        @(posedge rclk);
        while (!rempty) begin
            rinc = 1;
            @(posedge rclk);
        end
        
        // Overflow / Empty Read Case: Attempt extra read cycles when already empty
        repeat(5) @(posedge rclk);
        rinc = 0;

      #100;
        $finish;
    end

initial begin
    $dumpfile("dump.vcd");
    $dumpvars(0, async_fifo_tb);
end

endmodule

dump.vcd
$date
	Thu Jun 04 00:55:53 2026
$end
$version
	Icarus Verilog
$end
$timescale
	1ps
$end
$scope module async_fifo_tb $end
$var wire 1 ! wfull $end
$var wire 1 " rempty $end
$var wire 69 # rdata [68:0] $end
$var parameter 32 $ ADDR_WIDTH $end
$var parameter 32 % DATA_WIDTH $end
$var reg 1 & rclk $end
$var reg 1 ' rinc $end
$var reg 1 ( rrst_n $end
$var reg 1 ) wclk $end
$var reg 69 * wdata [68:0] $end
$var reg 1 + winc $end
$var reg 1 , wrst_n $end
$var integer 32 - i [31:0] $end
$scope module uut $end
$var wire 1 & rclk $end
$var wire 69 . rdata [68:0] $end
$var wire 1 ' rinc $end
$var wire 5 / rptr_gray [4:0] $end
$var wire 5 0 rptr_gray_next [4:0] $end
$var wire 1 ( rrst_n $end
$var wire 1 ) wclk $end
$var wire 69 1 wdata [68:0] $end
$var wire 1 + winc $end
$var wire 5 2 wptr_gray [4:0] $end
$var wire 5 3 wptr_gray_next [4:0] $end
$var wire 1 , wrst_n $end
$var wire 5 4 wptr_next [4:0] $end
$var wire 5 5 rptr_next [4:0] $end
$var parameter 32 6 ADDR_WIDTH $end
$var parameter 32 7 DATA_WIDTH $end
$var reg 1 " rempty $end
$var reg 5 8 rptr [4:0] $end
$var reg 5 9 rptr_gray_sync1 [4:0] $end
$var reg 5 : rptr_gray_sync2 [4:0] $end
$var reg 1 ! wfull $end
$var reg 5 ; wptr [4:0] $end
$var reg 5 < wptr_gray_sync1 [4:0] $end
$var reg 5 = wptr_gray_sync2 [4:0] $end
$upscope $end
$upscope $end
$enddefinitions $end
$comment Show the parameter values. $end
$dumpall
b1000101 7
b100 6
b1000101 %
b100 $
$end
#0
$dumpvars
b0 =
b0 <
b0 ;
b0 :
b0 9
b0 8
b0 5
b0 4
b0 3
b0 2
b0 1
b0 0
b0 /
bx .
bx -
0,
0+
b0 *
0)
0(
0'
0&
bx #
x"
0!
$end
#5000
1)
#10000
0)
#12000
1"
1&
#15000
1)
#20000
0)
#24000
0&
#25000
1)
#30000
0)
1(
1,
#35000
1)
#36000
1&
#40000
0)
#45000
1)
#48000
0&
#50000
0)
#55000
b1 2
b1 ;
b1 #
b1 .
b11 3
b10 4
b1 *
b1 1
1+
b1 -
1)
#60000
b1 <
0)
1&
#65000
b10 3
b11 2
b11 4
b10 ;
b10 *
b10 1
b10 -
1)
#70000
0)
#72000
0&
#75000
b110 3
b10 2
b100 4
b11 ;
b11 *
b11 1
b11 -
1)
#80000
0)
#84000
b1 =
b10 <
1&
#85000
b111 3
b110 2
b101 4
b100 ;
b100 *
b100 1
b100 -
1)
#90000
0)
#95000
b101 3
b111 2
b110 4
b101 ;
b101 *
b101 1
b101 -
1)
#96000
0&
#100000
0)
#105000
b100 3
b101 2
b111 4
b110 ;
b110 *
b110 1
b110 -
1)
#108000
b10 =
b101 <
0"
1&
#110000
0)
#115000
b1100 3
b100 2
b1000 4
b111 ;
b111 *
b111 1
b111 -
1)
#120000
0)
0&
#125000
b1101 3
b1100 2
b1001 4
b1000 ;
b1000 *
b1000 1
b1000 -
1)
#130000
0)
#132000
b101 =
b1100 <
1&
#135000
b1111 3
b1101 2
b1010 4
b1001 ;
b1001 *
b1001 1
b1001 -
1)
#140000
0)
#144000
0&
#145000
b1110 3
b1111 2
b1011 4
b1010 ;
b1010 *
b1010 1
b1010 -
1)
#150000
0)
#155000
b1010 3
b1110 2
b1100 4
b1011 ;
b1011 *
b1011 1
b1011 -
1)
#156000
b1100 =
b1110 <
1&
#160000
0)
#165000
b1011 3
b1010 2
b1101 4
b1100 ;
b1100 *
b1100 1
b1100 -
1)
#168000
0&
#170000
0)
#175000
b1001 3
b1011 2
b1110 4
b1101 ;
b1101 *
b1101 1
b1101 -
1)
#180000
b1110 =
b1011 <
0)
1&
#185000
b1000 3
b1001 2
b1111 4
b1110 ;
b1110 *
b1110 1
b1110 -
1)
#190000
0)
#192000
0&
#195000
b11000 3
b1000 2
b10000 4
b1111 ;
b1111 *
b1111 1
b1111 -
1)
#200000
0)
#204000
b1011 =
b1000 <
1&
#205000
b11000 3
b11000 2
1!
b10000 4
b10000 ;
b10000 *
b10000 1
b10000 -
1)
#210000
0)
#215000
b1111100111 *
b1111100111 1
b10001 -
1)
#216000
0&
#220000
0)
#225000
b10010 -
1)
#228000
b1000 =
b11000 <
1&
#230000
0)
#235000
b10011 -
1)
#240000
0)
0&
#245000
b10100 -
1)
#250000
0)
#252000
b11000 =
1&
#255000
0+
b10101 -
1)
